{
  "@context": "https://doi.org/10.5063/schema/codemeta-2.0",
  "@type": "SoftwareSourceCode",
  "identifier": "adlgraphs",
  "description": "The main goal of adlgraphs is to improve the efficiency and ease of cleaning, analyzing, and visualizing survey data, so that the turnaround time between data collection and presentation of analysis and findings can be as minimized. ",
  "name": "adlgraphs: Create Graphs with ADL Style and Branding",
  "relatedLink": "https://jdenn0514.github.io/adlgraphs/",
  "codeRepository": "https://github.com/JDenn0514/adlgraphs",
  "issueTracker": "https://github.com/JDenn0514/adlgraphs/issues",
  "license": "https://spdx.org/licenses/MIT",
  "version": "0.3.61",
  "programmingLanguage": {
    "@type": "ComputerLanguage",
    "name": "R",
    "url": "https://r-project.org"
  },
  "runtimePlatform": "R version 4.4.1 (2024-06-14)",
  "author": [
    {
      "@type": "Person",
      "givenName": "Jacob",
      "familyName": "Dennen",
      "email": "jdennen@adl.org"
    }
  ],
  "maintainer": [
    {
      "@type": "Person",
      "givenName": "Jacob",
      "familyName": "Dennen",
      "email": "jdennen@adl.org"
    }
  ],
  "softwareSuggestions": [
    {
      "@type": "SoftwareApplication",
      "identifier": "knitr",
      "name": "knitr",
      "provider": {
        "@id": "https://cran.r-project.org",
        "@type": "Organization",
        "name": "Comprehensive R Archive Network (CRAN)",
        "url": "https://cran.r-project.org"
      },
      "sameAs": "https://CRAN.R-project.org/package=knitr"
    },
    {
      "@type": "SoftwareApplication",
      "identifier": "rmarkdown",
      "name": "rmarkdown",
      "provider": {
        "@id": "https://cran.r-project.org",
        "@type": "Organization",
        "name": "Comprehensive R Archive Network (CRAN)",
        "url": "https://cran.r-project.org"
      },
      "sameAs": "https://CRAN.R-project.org/package=rmarkdown"
    },
    {
      "@type": "SoftwareApplication",
      "identifier": "testthat",
      "name": "testthat",
      "version": ">= 3.0.0",
      "provider": {
        "@id": "https://cran.r-project.org",
        "@type": "Organization",
        "name": "Comprehensive R Archive Network (CRAN)",
        "url": "https://cran.r-project.org"
      },
      "sameAs": "https://CRAN.R-project.org/package=testthat"
    },
    {
      "@type": "SoftwareApplication",
      "identifier": "labelled",
      "name": "labelled",
      "provider": {
        "@id": "https://cran.r-project.org",
        "@type": "Organization",
        "name": "Comprehensive R Archive Network (CRAN)",
        "url": "https://cran.r-project.org"
      },
      "sameAs": "https://CRAN.R-project.org/package=labelled"
    },
    {
      "@type": "SoftwareApplication",
      "identifier": "stringr",
      "name": "stringr",
      "provider": {
        "@id": "https://cran.r-project.org",
        "@type": "Organization",
        "name": "Comprehensive R Archive Network (CRAN)",
        "url": "https://cran.r-project.org"
      },
      "sameAs": "https://CRAN.R-project.org/package=stringr"
    }
  ],
  "softwareRequirements": {
    "1": {
      "@type": "SoftwareApplication",
      "identifier": "R",
      "name": "R",
      "version": ">= 4.4"
    },
    "2": {
      "@type": "SoftwareApplication",
      "identifier": "broom.helpers",
      "name": "broom.helpers",
      "provider": {
        "@id": "https://cran.r-project.org",
        "@type": "Organization",
        "name": "Comprehensive R Archive Network (CRAN)",
        "url": "https://cran.r-project.org"
      },
      "sameAs": "https://CRAN.R-project.org/package=broom.helpers"
    },
    "3": {
      "@type": "SoftwareApplication",
      "identifier": "cli",
      "name": "cli",
      "provider": {
        "@id": "https://cran.r-project.org",
        "@type": "Organization",
        "name": "Comprehensive R Archive Network (CRAN)",
        "url": "https://cran.r-project.org"
      },
      "sameAs": "https://CRAN.R-project.org/package=cli"
    },
    "4": {
      "@type": "SoftwareApplication",
      "identifier": "data.table",
      "name": "data.table",
      "provider": {
        "@id": "https://cran.r-project.org",
        "@type": "Organization",
        "name": "Comprehensive R Archive Network (CRAN)",
        "url": "https://cran.r-project.org"
      },
      "sameAs": "https://CRAN.R-project.org/package=data.table"
    },
    "5": {
      "@type": "SoftwareApplication",
      "identifier": "dplyr",
      "name": "dplyr",
      "provider": {
        "@id": "https://cran.r-project.org",
        "@type": "Organization",
        "name": "Comprehensive R Archive Network (CRAN)",
        "url": "https://cran.r-project.org"
      },
      "sameAs": "https://CRAN.R-project.org/package=dplyr"
    },
    "6": {
      "@type": "SoftwareApplication",
      "identifier": "forcats",
      "name": "forcats",
      "provider": {
        "@id": "https://cran.r-project.org",
        "@type": "Organization",
        "name": "Comprehensive R Archive Network (CRAN)",
        "url": "https://cran.r-project.org"
      },
      "sameAs": "https://CRAN.R-project.org/package=forcats"
    },
    "7": {
      "@type": "SoftwareApplication",
      "identifier": "furrr",
      "name": "furrr",
      "provider": {
        "@id": "https://cran.r-project.org",
        "@type": "Organization",
        "name": "Comprehensive R Archive Network (CRAN)",
        "url": "https://cran.r-project.org"
      },
      "sameAs": "https://CRAN.R-project.org/package=furrr"
    },
    "8": {
      "@type": "SoftwareApplication",
      "identifier": "ggplot2",
      "name": "ggplot2",
      "provider": {
        "@id": "https://cran.r-project.org",
        "@type": "Organization",
        "name": "Comprehensive R Archive Network (CRAN)",
        "url": "https://cran.r-project.org"
      },
      "sameAs": "https://CRAN.R-project.org/package=ggplot2"
    },
    "9": {
      "@type": "SoftwareApplication",
      "identifier": "glue",
      "name": "glue",
      "provider": {
        "@id": "https://cran.r-project.org",
        "@type": "Organization",
        "name": "Comprehensive R Archive Network (CRAN)",
        "url": "https://cran.r-project.org"
      },
      "sameAs": "https://CRAN.R-project.org/package=glue"
    },
    "10": {
      "@type": "SoftwareApplication",
      "identifier": "grDevices",
      "name": "grDevices"
    },
    "11": {
      "@type": "SoftwareApplication",
      "identifier": "gt",
      "name": "gt",
      "provider": {
        "@id": "https://cran.r-project.org",
        "@type": "Organization",
        "name": "Comprehensive R Archive Network (CRAN)",
        "url": "https://cran.r-project.org"
      },
      "sameAs": "https://CRAN.R-project.org/package=gt"
    },
    "12": {
      "@type": "SoftwareApplication",
      "identifier": "gto",
      "name": "gto",
      "provider": {
        "@id": "https://cran.r-project.org",
        "@type": "Organization",
        "name": "Comprehensive R Archive Network (CRAN)",
        "url": "https://cran.r-project.org"
      },
      "sameAs": "https://CRAN.R-project.org/package=gto"
    },
    "13": {
      "@type": "SoftwareApplication",
      "identifier": "highcharter",
      "name": "highcharter",
      "provider": {
        "@id": "https://cran.r-project.org",
        "@type": "Organization",
        "name": "Comprehensive R Archive Network (CRAN)",
        "url": "https://cran.r-project.org"
      },
      "sameAs": "https://CRAN.R-project.org/package=highcharter"
    },
    "14": {
      "@type": "SoftwareApplication",
      "identifier": "haven",
      "name": "haven",
      "provider": {
        "@id": "https://cran.r-project.org",
        "@type": "Organization",
        "name": "Comprehensive R Archive Network (CRAN)",
        "url": "https://cran.r-project.org"
      },
      "sameAs": "https://CRAN.R-project.org/package=haven"
    },
    "15": {
      "@type": "SoftwareApplication",
      "identifier": "jtools",
      "name": "jtools",
      "provider": {
        "@id": "https://cran.r-project.org",
        "@type": "Organization",
        "name": "Comprehensive R Archive Network (CRAN)",
        "url": "https://cran.r-project.org"
      },
      "sameAs": "https://CRAN.R-project.org/package=jtools"
    },
    "16": {
      "@type": "SoftwareApplication",
      "identifier": "lifecycle",
      "name": "lifecycle",
      "provider": {
        "@id": "https://cran.r-project.org",
        "@type": "Organization",
        "name": "Comprehensive R Archive Network (CRAN)",
        "url": "https://cran.r-project.org"
      },
      "sameAs": "https://CRAN.R-project.org/package=lifecycle"
    },
    "17": {
      "@type": "SoftwareApplication",
      "identifier": "mvtnorm",
      "name": "mvtnorm",
      "provider": {
        "@id": "https://cran.r-project.org",
        "@type": "Organization",
        "name": "Comprehensive R Archive Network (CRAN)",
        "url": "https://cran.r-project.org"
      },
      "sameAs": "https://CRAN.R-project.org/package=mvtnorm"
    },
    "18": {
      "@type": "SoftwareApplication",
      "identifier": "officer",
      "name": "officer",
      "provider": {
        "@id": "https://cran.r-project.org",
        "@type": "Organization",
        "name": "Comprehensive R Archive Network (CRAN)",
        "url": "https://cran.r-project.org"
      },
      "sameAs": "https://CRAN.R-project.org/package=officer"
    },
    "19": {
      "@type": "SoftwareApplication",
      "identifier": "prismatic",
      "name": "prismatic",
      "provider": {
        "@id": "https://cran.r-project.org",
        "@type": "Organization",
        "name": "Comprehensive R Archive Network (CRAN)",
        "url": "https://cran.r-project.org"
      },
      "sameAs": "https://CRAN.R-project.org/package=prismatic"
    },
    "20": {
      "@type": "SoftwareApplication",
      "identifier": "psych",
      "name": "psych",
      "provider": {
        "@id": "https://cran.r-project.org",
        "@type": "Organization",
        "name": "Comprehensive R Archive Network (CRAN)",
        "url": "https://cran.r-project.org"
      },
      "sameAs": "https://CRAN.R-project.org/package=psych"
    },
    "21": {
      "@type": "SoftwareApplication",
      "identifier": "purrr",
      "name": "purrr",
      "provider": {
        "@id": "https://cran.r-project.org",
        "@type": "Organization",
        "name": "Comprehensive R Archive Network (CRAN)",
        "url": "https://cran.r-project.org"
      },
      "sameAs": "https://CRAN.R-project.org/package=purrr"
    },
    "22": {
      "@type": "SoftwareApplication",
      "identifier": "readr",
      "name": "readr",
      "provider": {
        "@id": "https://cran.r-project.org",
        "@type": "Organization",
        "name": "Comprehensive R Archive Network (CRAN)",
        "url": "https://cran.r-project.org"
      },
      "sameAs": "https://CRAN.R-project.org/package=readr"
    },
    "23": {
      "@type": "SoftwareApplication",
      "identifier": "rlang",
      "name": "rlang",
      "provider": {
        "@id": "https://cran.r-project.org",
        "@type": "Organization",
        "name": "Comprehensive R Archive Network (CRAN)",
        "url": "https://cran.r-project.org"
      },
      "sameAs": "https://CRAN.R-project.org/package=rlang"
    },
    "24": {
      "@type": "SoftwareApplication",
      "identifier": "rstudioapi",
      "name": "rstudioapi",
      "provider": {
        "@id": "https://cran.r-project.org",
        "@type": "Organization",
        "name": "Comprehensive R Archive Network (CRAN)",
        "url": "https://cran.r-project.org"
      },
      "sameAs": "https://CRAN.R-project.org/package=rstudioapi"
    },
    "25": {
      "@type": "SoftwareApplication",
      "identifier": "stats",
      "name": "stats"
    },
    "26": {
      "@type": "SoftwareApplication",
      "identifier": "systemfonts",
      "name": "systemfonts",
      "provider": {
        "@id": "https://cran.r-project.org",
        "@type": "Organization",
        "name": "Comprehensive R Archive Network (CRAN)",
        "url": "https://cran.r-project.org"
      },
      "sameAs": "https://CRAN.R-project.org/package=systemfonts"
    },
    "27": {
      "@type": "SoftwareApplication",
      "identifier": "tibble",
      "name": "tibble",
      "provider": {
        "@id": "https://cran.r-project.org",
        "@type": "Organization",
        "name": "Comprehensive R Archive Network (CRAN)",
        "url": "https://cran.r-project.org"
      },
      "sameAs": "https://CRAN.R-project.org/package=tibble"
    },
    "28": {
      "@type": "SoftwareApplication",
      "identifier": "tidyr",
      "name": "tidyr",
      "provider": {
        "@id": "https://cran.r-project.org",
        "@type": "Organization",
        "name": "Comprehensive R Archive Network (CRAN)",
        "url": "https://cran.r-project.org"
      },
      "sameAs": "https://CRAN.R-project.org/package=tidyr"
    },
    "29": {
      "@type": "SoftwareApplication",
      "identifier": "tidyselect",
      "name": "tidyselect",
      "provider": {
        "@id": "https://cran.r-project.org",
        "@type": "Organization",
        "name": "Comprehensive R Archive Network (CRAN)",
        "url": "https://cran.r-project.org"
      },
      "sameAs": "https://CRAN.R-project.org/package=tidyselect"
    },
    "30": {
      "@type": "SoftwareApplication",
      "identifier": "withr",
      "name": "withr",
      "provider": {
        "@id": "https://cran.r-project.org",
        "@type": "Organization",
        "name": "Comprehensive R Archive Network (CRAN)",
        "url": "https://cran.r-project.org"
      },
      "sameAs": "https://CRAN.R-project.org/package=withr"
    },
    "31": {
      "@type": "SoftwareApplication",
      "identifier": "writexl",
      "name": "writexl",
      "provider": {
        "@id": "https://cran.r-project.org",
        "@type": "Organization",
        "name": "Comprehensive R Archive Network (CRAN)",
        "url": "https://cran.r-project.org"
      },
      "sameAs": "https://CRAN.R-project.org/package=writexl"
    },
    "32": {
      "@type": "SoftwareApplication",
      "identifier": "vctrs",
      "name": "vctrs",
      "provider": {
        "@id": "https://cran.r-project.org",
        "@type": "Organization",
        "name": "Comprehensive R Archive Network (CRAN)",
        "url": "https://cran.r-project.org"
      },
      "sameAs": "https://CRAN.R-project.org/package=vctrs"
    },
    "SystemRequirements": null
  },
  "fileSize": "815.097KB"
}
